{
    "special fields": [
        { "id": "id", "label": "Identifier", "icon": "beenhere", "desc": "An identifier for each row such as company name. While not compulsory it makes sense to usually have an identifier" },
        { "id": "status", "label": "Status", "icon": "verified", "config": "options", "desc": "Track a row through configurable steps or stages such as todo, doing, done" },
        { "id": "assigned", "label": "Assigned", "icon": "person", "config": "user", "desc": "Assign the row to a person in your orginisation" },
        { "id": "start", "label": "Start Date", "icon": "today", "config": "date", "desc": "The date/time an activity started" },
        { "id": "due", "label": "Due Date", "icon": "event", "config": "date", "desc": "The date/time an activity is due" },
        { "id": "completed", "label": "Completion Date", "icon": "event_available", "config": "date", "desc": "The date/time an activity completed" }
    ],
    "data input": [
        { "id": "text", "label": "Text", "icon": "text_fields", "desc": "A generic line of text" },
        { "id": "multi", "label": "Rich text", "icon": "menu", "desc": "Multiple lines of optionally formatted text" },
        { "id": "number", "label": "Number", "icon": "123", "config": "number", "desc": "A generic numeric value" },
        { "id": "currency", "label": "Currency", "icon": "attach_money", "config": "currency", "desc": "Monetary values" },
        { "id": "date", "label": "Date", "icon": "calendar_today", "config": "date", "desc": "A generic date/time" },

        { "id": "check", "label": "Check", "icon": "check_box", "desc": "Check or uncheck to indicate status" },
        { "id": "select", "label": "Single select", "icon": "playlist_add_check", "desc": "Pick one value" },
        { "id": "label", "label": "Labels", "icon": "checklist_rtl", "desc": "Tag a row with multiple values" },
        { "id": "user", "label": "Person", "icon": "person", "desc": "One or more people in your organisation" },

        { "id": "address", "label": "Address", "icon": "location_on", "desc": "A valid address" },
        { "id": "phone", "label": "Phone number", "icon": "call", "desc": "A valid telephone number" },
        { "id": "email", "label": "Email", "icon": "mail", "desc": "A valid email address" },
        { "id": "link", "label": "Link", "icon": "link", "desc": "A link to a web site or page" },

        { "id": "priority", "label": "Priority", "icon": "personal_places", "desc": "An indicator of a rows priority" },
        { "id": "rateing", "label": "Rating", "icon": "star", "desc": "An indicater of a rows rating" }
    ],
    "calculated": [
        { "id": "percent", "label": "Percent", "icon": "percent", "desc": "A percentage calculated from another field" },
        { "id": "duration", "label": "Duration", "icon": "timelapse", "desc": "" },
        { "id": "created", "label": "Created", "icon": "more_time", "desc": "Automatic timestamp when the row was created" },
        { "id": "modified", "label": "Last modified", "icon": "history", "desc": "Automatic timestamp when the row was last modified" },
        { "id": "created-by", "label": "Created by", "icon": "person_add", "desc": "Automatic stamp of who created the row" },
        { "id": "modified-by", "label": "Last modified by", "icon": "person_search", "desc": "Automatic stamp of Who last modified the row" },
        { "id": "auto", "label": "Autonumber", "icon": "exposure_plus_1", "desc": "Automatically generate a unique number" },
        { "id": "formula", "label": "Formula", "icon": "function", "desc": "Calculate a value based on other fields" },
        { "id": "rollup", "label": "Rollup", "icon": "keyboard_double_arrow_up", "desc": "" },
        { "id": "count", "label": "Count", "icon": "functions", "desc": "" },
        { "id": "lookup", "label": "Lookup", "icon": "manage_search", "desc": "" }
    ],
    "misc": [
        { "id": "join", "label": "Link to another record", "icon": "join", "desc": "" },
        { "id": "attachment", "label": "Attachment", "icon": "attachment", "desc": "Attach files to a row" },
        { "id": "qr", "label": "QR code", "icon": "qr_code", "desc": "Generate a QR code of another field" },
        { "id": "button", "label": "Button", "icon": "crop_16_9", "desc": "Perform an action on the row" }
    ]
}
